geminicontrolpc/__init__.py
geminicontrolpc/geminicontrolpc.py
geminicontrolpc-0.1.7.dist-info/METADATA
geminicontrolpc-0.1.7.dist-info/WHEEL
geminicontrolpc-0.1.7.dist-info/entry_points.txt
geminicontrolpc-0.1.7.dist-info/top_level.txt
geminicontrolpc-0.1.7.dist-info/RECORD
