Metadata-Version: 2.1
Name: geminicontrolpc
Version: 0.1.7
Summary: A Python package for controlling your PC using Google Gemini AI.
Home-page: https://github.com/gigachadtrey/geminicontrolpc
Author: Trey Leonard
Author-email: allanleonardiii@gmail.com
Classifier: Programming Language :: Python :: 3
Classifier: License :: OSI Approved :: MIT License
Classifier: Operating System :: OS Independent
Requires-Python: >=3.6
Requires-Dist: google-generativeai>=0.1.0
Requires-Dist: Pillow>=8.0.0
Requires-Dist: opencv-python>=4.0.0
